[
  {
    "flight_number": "SN2556",
    "airline": "Brussels Airlines",
    "status": "Estimated dep 18:05",
    "destination_city": "Brussels",
    "expected_departure_time": 1705950600
  },
  {
    "flight_number": "W61465",
    "airline": "Wizz Air",
    "status": "Estimated dep 18:05",
    "destination_city": "Bologna",
    "expected_departure_time": 1705950600
  },
  {
    "flight_number": "A3873",
    "airline": "Aegean Airlines",
    "status": "Estimated dep 18:15",
    "destination_city": "Athens",
    "expected_departure_time": 1705952700
  },
  {
    "flight_number": "LO531",
    "airline": "LOT",
    "status": "Estimated dep 19:00",
    "destination_city": "Budapest",
    "expected_departure_time": 1705948800
  },
  {
    "flight_number": "LY5102",
    "airline": "El Al",
    "status": "Estimated dep 18:30",
    "destination_city": "Tel Aviv",
    "expected_departure_time": 1705957800
  },
  {
    "flight_number": "SK2752",
    "airline": "Cityjet",
    "status": "Estimated dep 18:50",
    "destination_city": "Copenhagen",
    "expected_departure_time": 1705950900
  },
  {
    "flight_number": "LH1351",
    "airline": "Lufthansa",
    "status": "Estimated dep 18:55",
    "destination_city": "Frankfurt",
    "expected_departure_time": 1705953000
  },
  {
    "flight_number": "AY1146",
    "airline": "NORRA",
    "status": "Estimated dep 21:15",
    "destination_city": "Helsinki",
    "expected_departure_time": 1705955700
  },
  {
    "flight_number": "LO6519",
    "airline": "LOT",
    "status": "Estimated dep 19:30",
    "destination_city": "Bangkok",
    "expected_departure_time": 1705981980
  },
  {
    "flight_number": "LO3935",
    "airline": "LOT",
    "status": "Estimated dep 19:20",
    "destination_city": "Szczecin",
    "expected_departure_time": 1705951500
  }
]